dae_transer/__init__.py
dae_transer/__main__.py
dae_transer/config/__init__.py
dae_transer/downloader/__init__.py
dae_transer/downloader/session.py
dae_transer/exceptions/__init__.py
dae_transer/log/__init__.py
dae_transer/parse/__init__.py
dae_transer/worker/__init__.py
dae_transer/worker/detail.py
dae_transer/worker/utils.py
dae_transer/worker/vars.py
dae_transer-0.2.3.dist-info/METADATA
dae_transer-0.2.3.dist-info/WHEEL
dae_transer-0.2.3.dist-info/entry_points.txt
dae_transer-0.2.3.dist-info/top_level.txt
dae_transer-0.2.3.dist-info/RECORD
