Metadata-Version: 2.1
Name: dae_transer
Version: 0.2.3
Summary: dae机场订阅转换工具
Home-page: 
Author: TT
Author-email: 123@mail.com
License: BSD
Keywords: dae_transer
Platform: Linux
Classifier: Programming Language :: Python :: 3.10
Classifier: Programming Language :: Python :: 3.11
Classifier: Programming Language :: Python :: 3.12
Classifier: Programming Language :: Python :: 3.13
Classifier: Operating System :: POSIX :: Linux
Requires-Python: >=3.10.4
Requires-Dist: requests
Requires-Dist: PyYAML
Requires-Dist: funcy
Requires-Dist: Brotli
Requires-Dist: jinja2
Requires-Dist: pypinyin
